butchertableau/__init__.py
butchertableau/butcher.py
butchertableau/butcherex.py
butchertableau/butchertableau.py
butchertableau/matrixfuncs.py
butchertableau-1.0.9.dist-info/LICENSE
butchertableau-1.0.9.dist-info/METADATA
butchertableau-1.0.9.dist-info/WHEEL
butchertableau-1.0.9.dist-info/top_level.txt
butchertableau-1.0.9.dist-info/RECORD
