Metadata-Version: 2.1
Name: butchertableau
Version: 1.0.9
Summary: Calculates the butcher tableau for a given order.
Home-page: https://github.com/tjczec01/butcher
Author: Travis Czechorski
Author-email: tjczec01@gmail.com
License: UNKNOWN
Keywords: chemical engineering,chemistry,engineering,chemical reactions,Butcher Tableau,Radau,Numerical
Platform: UNKNOWN
Classifier: Programming Language :: Python :: 3
Classifier: License :: OSI Approved :: MIT License
Classifier: Operating System :: OS Independent
Requires-Python: >=3.6
License-File: LICENSE
